<?xml version="1.0" encoding="UTF-8"?>
<!DOCTYPE nitf SYSTEM "http://www.nitf.org/IPTC/NITF/3.3/specification/dtd/nitf-3-3.dtd">
<nitf change.date="June 10, 2005" change.time="19:30" version="-//IPTC//DTD NITF 3.3//EN">
  <head>
    <title>May 31-June 6; A Zambian, Freed</title>
    <meta content="07P2ST$02" name="slug"/>
    <meta content="7" name="publication_day_of_month"/>
    <meta content="6" name="publication_month"/>
    <meta content="1998" name="publication_year"/>
    <meta content="Sunday" name="publication_day_of_week"/>
    <meta content="Week in Review Desk" name="dsk"/>
    <meta content="2" name="print_page_number"/>
    <meta content="4" name="print_section"/>
    <meta content="4" name="print_column"/>
    <meta content="Week in Review" name="online_sections"/>
    <docdata>
      <doc-id id-string="1022864"/>
      <doc.copyright holder="The New York Times" year="1998"/>
      <identified-content>
        <classifier class="indexing_service" type="descriptor">NO INDEX TERMS FROM NYTIMES</classifier>
        <classifier class="online_producer" type="taxonomic_classifier">Top/Features/Week in Review</classifier>
      </identified-content>
    </docdata>
    <pubdata date.publication="19980607T000000" ex-ref="http://query.nytimes.com/gst/fullpage.html?res=9906EEDE1F3BF934A35755C0A96E958260" item-length="151" name="The New York Times" unit-of-measure="word"/>
  </head>
  <body>
    <body.head>
      <hedline>
        <hl1>May 31-June 6; A Zambian, Freed</hl1>
      </hedline>
      <byline class="print_byline">By DONALD G. McNEIL Jr.</byline>
    </body.head>
    <body.content>
      <block class="lead_paragraph">
        <p>Kenneth D. Kaunda, one of Africa's grand old men, is a free man again. After keeping the former President in jail or under house arrest for more than five months,  Zambian prosecutors dropped all charges against him. Their case had always looked weak. Mr. Kaunda was originally accused of plotting a bungled coup attempt last October.</p>
      </block>
      <block class="full_text">
        <p>Kenneth D. Kaunda, one of Africa's grand old men, is a free man again. After keeping the former President in jail or under house arrest for more than five months,  Zambian prosecutors dropped all charges against him. Their case had always looked weak. Mr. Kaunda was originally accused of plotting a bungled coup attempt last October.</p>
        <p>Diplomatic sources said President Nelson Mandela of South Africa brokered a deal -- free Mr. Kaunda, who ruled Zambia from 1964 to 1991, and he would return to retirement. But probably not quietly.</p>
        <p>DONALD G. McNEIL Jr.</p>
      </block>
    </body.content>
  </body>
</nitf>
