<?xml version="1.0" encoding="UTF-8"?>
<!DOCTYPE nitf SYSTEM "http://www.nitf.org/IPTC/NITF/3.3/specification/dtd/nitf-3-3.dtd">
<nitf change.date="June 10, 2005" change.time="19:30" version="-//IPTC//DTD NITF 3.3//EN">
  <head>
    <title>Paid Notice: Deaths  JENNINGS, EDWARD</title>
    <meta content="DN011998" name="slug"/>
    <meta content="19" name="publication_day_of_month"/>
    <meta content="1" name="publication_month"/>
    <meta content="1998" name="publication_year"/>
    <meta content="Monday" name="publication_day_of_week"/>
    <meta content="Classified" name="dsk"/>
    <meta content="15" name="print_page_number"/>
    <meta content="A" name="print_section"/>
    <meta content="3" name="print_column"/>
    <meta content="Paid Death Notices" name="online_sections"/>
    <docdata>
      <doc-id id-string="988789"/>
      <doc.copyright holder="The New York Times" year="1998"/>
      <identified-content>
        <person class="indexing_service">JENNINGS, EDWARD</person>
        <classifier class="online_producer" type="types_of_material">Paid Death Notice</classifier>
        <classifier class="online_producer" type="taxonomic_classifier">Top/Classifieds/Paid Death Notices</classifier>
      </identified-content>
    </docdata>
    <pubdata date.publication="19980119T000000" ex-ref="http://query.nytimes.com/gst/fullpage.html?res=9C02E0DB1738F93AA25752C0A96E958260" item-length="109" name="The New York Times" unit-of-measure="word"/>
  </head>
  <body>
    <body.head>
      <hedline>
        <hl1>Paid Notice: Deaths  JENNINGS, EDWARD</hl1>
      </hedline>
    </body.head>
    <body.content>
      <block class="lead_paragraph">
        <p>JENNINGS-Edward. On January 17, 1998, of Long Boat Key, FL, formerly of Mamaroneck, NY. Beloved husband of the late Molly Jennings. Loving brother of John, Thomas, Patrick, Mary, Bridget, Angela, and the late Tobias. Also survived by several nieces and nephews. The family will receive friends Monday, 2-4, 7-9 PM at the William H. Graham Funeral Home, 1036 Boston Post Rd., Rye, NY. Mass of Christian Burial Tuesday, 10 AM, at the Church of the Resurrection, Rye, NY. Interment to follow at Long Island National Cemetery, Pinelawn, NY. In lieu of flowers, contributions may be made to the Lung Cancer Service, Memorial Sloan-Kettering, 1275 York Ave., New York, NY.</p>
      </block>
      <block class="full_text">
        <p>JENNINGS-Edward. On January 17, 1998, of Long Boat Key, FL, formerly of Mamaroneck, NY. Beloved husband of the late Molly Jennings. Loving brother of John, Thomas, Patrick, Mary, Bridget, Angela, and the late Tobias. Also survived by several nieces and nephews. The family will receive friends Monday, 2-4, 7-9 PM at the William H. Graham Funeral Home, 1036 Boston Post Rd., Rye, NY. Mass of Christian Burial Tuesday, 10 AM, at the Church of the Resurrection, Rye, NY. Interment to follow at Long Island National Cemetery, Pinelawn, NY. In lieu of flowers, contributions may be made to the Lung Cancer Service, Memorial Sloan-Kettering, 1275 York Ave., New York, NY.</p>
      </block>
    </body.content>
  </body>
</nitf>
